<url>
<loc>https://ilyricstape.blogspot.com/</loc>
<lastmod>2025-04-06T12:15:06+00:00</lastmod>
<priority>1.00</priority>
</url>
<url>
<loc>https://ilyricstape.blogspot.com/p/pushpa-title-telugu-lyrics.html</loc>
<lastmod>2025-04-06T12:15:06+00:00</lastmod>
<priority>0.80</priority>
</url>
<url>
<loc>https://ilyricstape.blogspot.com/p/kissik-telugu-lyrics.html</loc>
<lastmod>2025-04-06T12:15:06+00:00</lastmod>
<priority>0.80</priority>
</url>
<url>
<loc>https://ilyricstape.blogspot.com/p/gango-renuka-thalli-telugu-lyrics.html</loc>
<lastmod>2025-04-06T12:15:06+00:00</lastmod>
<priority>0.80</priority>
</url>
<url>
<loc>https://ilyricstape.blogspot.com/p/sooseki-telugu-lyrics.html</loc>
<lastmod>2025-04-06T12:15:06+00:00</lastmod>
<priority>0.80</priority>
</url>
<url>
<loc>https://ilyricstape.blogspot.com/p/bujji-talli-telugu-lyrics.html</loc>
<lastmod>2025-04-06T12:15:06+00:00</lastmod>
<priority>0.80</priority>
</url>
<url>
<loc>https://ilyricstape.blogspot.com/p/chiru-chiru-telugu-lyrics.html</loc>
<lastmod>2025-04-06T12:15:06+00:00</lastmod>
<priority>0.80</priority>
</url>
<url>
<loc>https://ilyricstape.blogspot.com/p/kurchi-madathapetti-telugu-lyrics.html</loc>
<lastmod>2025-04-06T12:15:06+00:00</lastmod>
<priority>0.80</priority>
</url>
<url>
<loc>https://ilyricstape.blogspot.com/p/peelings-telugu-lyrics.html</loc>
<lastmod>2025-04-06T12:15:06+00:00</lastmod>
<priority>0.64</priority>
</url>
</urlset>
